{
  "accentColor": "{{appsmith.theme.colors.primaryColor}}",
  "animateLoading": true,
  "borderRadius": "{{appsmith.theme.borderRadius.appBorderRadius}}",
  "bottomRow": 21,
  "boxShadow": "none",
  "closeOnSelection": true,
  "dateFormat": "DD/MM/YYYY",
  "datePickerType": "DATE_PICKER",
  "defaultDate": "{{\nappsmith.store.modoNC === \"MODIFICAR\"\n    ? NCModificarEncabezado.data[0]?.fecha_nota\n    : \"\"\n}}",
  "dynamicBindingPathList": [
    {
      "key": "accentColor"
    },
    {
      "key": "borderRadius"
    },
    {
      "key": "defaultDate"
    }
  ],
  "dynamicHeight": "FIXED",
  "dynamicPropertyPathList": [
    {
      "key": "defaultDate"
    }
  ],
  "dynamicTriggerPathList": [],
  "firstDayOfWeek": 0,
  "isDisabled": false,
  "isLoading": false,
  "isRequired": false,
  "isVisible": true,
  "key": "p24az67cdi",
  "label": "Fecha",
  "labelAlignment": "left",
  "labelPosition": "Top",
  "labelTextSize": "0.875rem",
  "labelWidth": 5,
  "leftColumn": 21,
  "maxDate": "2121-12-31T18:29:00.000Z",
  "maxDynamicHeight": 9000,
  "minDate": "1920-12-31T18:30:00.000Z",
  "minDynamicHeight": 4,
  "minWidth": 450,
  "mobileBottomRow": 21,
  "mobileLeftColumn": 21,
  "mobileRightColumn": 41,
  "mobileTopRow": 14,
  "needsErrorInfo": false,
  "parentColumnSpace": 19.625,
  "parentId": "ffs7wvbj4s",
  "parentRowSpace": 10,
  "renderMode": "CANVAS",
  "responsiveBehavior": "fill",
  "rightColumn": 33,
  "shortcuts": false,
  "timePrecision": "minute",
  "topRow": 14,
  "type": "DATE_PICKER_WIDGET2",
  "version": 2,
  "widgetId": "rbse8jaq74",
  "widgetName": "dpFechaNC"
}