{
  "accentColor": "{{appsmith.theme.colors.primaryColor}}",
  "animateLoading": true,
  "autoFocus": false,
  "borderRadius": "{{appsmith.theme.borderRadius.appBorderRadius}}",
  "bottomRow": 36,
  "boxShadow": "none",
  "defaultText": "{{ tblConsultaSP.selectedRow.concepto }}",
  "dynamicBindingPathList": [
    {
      "key": "accentColor"
    },
    {
      "key": "borderRadius"
    },
    {
      "key": "defaultText"
    }
  ],
  "dynamicHeight": "AUTO_HEIGHT",
  "dynamicTriggerPathList": [],
  "iconAlign": "left",
  "inputType": "MULTI_LINE_TEXT",
  "isDisabled": true,
  "isLoading": false,
  "isRequired": false,
  "isVisible": true,
  "key": "ceojg65ho3",
  "label": "Concepto",
  "labelAlignment": "left",
  "labelPosition": "Top",
  "labelStyle": "BOLD",
  "labelTextSize": "0.875rem",
  "labelWidth": 5,
  "leftColumn": 0,
  "maxDynamicHeight": 9000,
  "minDynamicHeight": 4,
  "minWidth": 450,
  "mobileBottomRow": 33,
  "mobileLeftColumn": 0,
  "mobileRightColumn": 20,
  "mobileTopRow": 26,
  "needsErrorInfo": false,
  "originalBottomRow": 36,
  "originalTopRow": 26,
  "parentColumnSpace": 19.3125,
  "parentId": "gl3y8epq7m",
  "parentRowSpace": 10,
  "renderMode": "CANVAS",
  "resetOnSubmit": true,
  "responsiveBehavior": "fill",
  "rightColumn": 20,
  "shouldAllowAutofill": false,
  "showStepArrows": false,
  "topRow": 26,
  "type": "INPUT_WIDGET_V2",
  "version": 2,
  "widgetId": "3cjxkb3ww2",
  "widgetName": "inpConcepto_SP_tblConSel"
}