{
  "accentColor": "{{appsmith.theme.colors.primaryColor}}",
  "animateLoading": true,
  "autoFocus": false,
  "borderRadius": "{{appsmith.theme.borderRadius.appBorderRadius}}",
  "bottomRow": 38,
  "boxShadow": "none",
  "defaultText": "{{\nappsmith.store.modoAV === \"MODIFICAR\"\n  ? (appsmith.store.encabezadoAV?.monto_retencion_tss ?? \"\")\n  : (appsmith.store.avanceActual?.retencion_tss_posible ?? \"\")\n}}",
  "dynamicBindingPathList": [
    {
      "key": "accentColor"
    },
    {
      "key": "borderRadius"
    },
    {
      "key": "defaultText"
    }
  ],
  "dynamicHeight": "FIXED",
  "dynamicTriggerPathList": [],
  "iconAlign": "left",
  "inputType": "TEXT",
  "isDisabled": false,
  "isLoading": false,
  "isRequired": false,
  "isVisible": true,
  "key": "8yl4udmb79",
  "label": "Retención TSS",
  "labelAlignment": "left",
  "labelPosition": "Top",
  "labelStyle": "",
  "labelTextSize": "0.875rem",
  "labelWidth": 5,
  "leftColumn": 41,
  "maxDynamicHeight": 9000,
  "minDynamicHeight": 4,
  "minWidth": 450,
  "mobileBottomRow": 31,
  "mobileLeftColumn": 39,
  "mobileRightColumn": 59,
  "mobileTopRow": 24,
  "needsErrorInfo": false,
  "originalBottomRow": 129,
  "originalTopRow": 122,
  "parentColumnSpace": 19.3125,
  "parentId": "09p72t8ya1",
  "parentRowSpace": 10,
  "renderMode": "CANVAS",
  "resetOnSubmit": true,
  "responsiveBehavior": "fill",
  "rightColumn": 53,
  "showStepArrows": false,
  "topRow": 31,
  "type": "INPUT_WIDGET_V2",
  "version": 2,
  "widgetId": "m3ickpkh80",
  "widgetName": "inpRetencionTSS_AV"
}